README.md
setup.cfg
setup.py
hsdbi/__init__.py
hsdbi/base.py
hsdbi/errors.py
hsdbi/mongo.py
hsdbi/sql.py
hsdbi.egg-info/PKG-INFO
hsdbi.egg-info/SOURCES.txt
hsdbi.egg-info/dependency_links.txt
hsdbi.egg-info/requires.txt
hsdbi.egg-info/top_level.txt