Metadata-Version: 1.1
Name: hsdbi
Version: 0.1a17
Summary: A simple interface for accessing databases.
Home-page: https://github.com/timniven/hsdbi
Author: Tim Niven
Author-email: tim.niven.public@gmail.com
License: MIT
Download-URL: https://github.com/timniven/hsdbi/archive/0.1a17.tar.gz
Keywords: database interface facade
Platform: UNKNOWN
Classifier: Development Status :: 3 - Alpha
Classifier: Intended Audience :: Developers
Classifier: Topic :: Software Development :: Libraries :: Python Modules
Classifier: Programming Language :: Python :: 3
Classifier: License :: OSI Approved :: MIT License
